{
    "ok":  true,
    "namespace":  "pencil_engine/J58_custom",
    "stamp":  "20250925-192150",
    "created_utc":  "2025-09-25T10:21:51Z",
    "runs":  {
                 "J58":  {
                             "run_dir":  "run-20250925-192149",
                             "parts":  [
                                           "afterburner_shell_L.stl",
                                           "afterburner_shell_R.stl",
                                           "base_frame.stl",
                                           "bearing_holder_L_L.stl",
                                           "bearing_holder_L_R.stl",
                                           "bearing_holder_R_L.stl",
                                           "bearing_holder_R_R.stl",
                                           "bearing_rail_L_L.stl",
                                           "bearing_rail_L_R.stl",
                                           "bearing_rail_R_L.stl",
                                           "bearing_rail_R_R.stl",
                                           "belt_L_stub.stl",
                                           "belt_R_stub.stl",
                                           "casing_aft_L.stl",
                                           "casing_aft_R.stl",
                                           "casing_front_L.stl",
                                           "casing_front_R.stl",
                                           "casing_mid_L.stl",
                                           "casing_mid_R.stl",
                                           "combustor_shell_L.stl",
                                           "combustor_shell_R.stl",
                                           "comp_rotor_L.stl",
                                           "comp_rotor_R.stl",
                                           "comp_stator_L.stl",
                                           "comp_stator_R.stl",
                                           "fan_rotor_L.stl",
                                           "fan_rotor_R.stl",
                                           "fan_stator_L.stl",
                                           "fan_stator_R.stl",
                                           "inlet_spike_L.stl",
                                           "inlet_spike_R.stl",
                                           "nozzle_cone_L.stl",
                                           "nozzle_cone_R.stl",
                                           "pulley_engine_L.stl",
                                           "pulley_engine_R.stl",
                                           "pulley_motor.stl",
                                           "rib_1_L.stl",
                                           "rib_1_R.stl",
                                           "rib_2_L.stl",
                                           "rib_2_R.stl",
                                           "rib_3_L.stl",
                                           "rib_3_R.stl",
                                           "rib_4_L.stl",
                                           "rib_4_R.stl",
                                           "rib_5_L.stl",
                                           "rib_5_R.stl",
                                           "rib_6_L.stl",
                                           "rib_6_R.stl",
                                           "seat_comp_L.stl",
                                           "seat_comp_R.stl",
                                           "seat_fan_L.stl",
                                           "seat_fan_R.stl",
                                           "seat_turb_L.stl",
                                           "seat_turb_R.stl",
                                           "shaft_main_L.stl",
                                           "shaft_main_R.stl",
                                           "spacer_1_L.stl",
                                           "spacer_1_R.stl",
                                           "spacer_2_L.stl",
                                           "spacer_2_R.stl",
                                           "spacer_3_L.stl",
                                           "spacer_3_R.stl",
                                           "spacer_4_L.stl",
                                           "spacer_4_R.stl",
                                           "spacer_5_L.stl",
                                           "spacer_5_R.stl",
                                           "spacer_6_L.stl",
                                           "spacer_6_R.stl",
                                           "splice_front_mid_L.stl",
                                           "splice_front_mid_R.stl",
                                           "splice_mid_aft_L.stl",
                                           "splice_mid_aft_R.stl",
                                           "starter_motor_130.stl",
                                           "turb_rotor_L.stl",
                                           "turb_rotor_R.stl",
                                           "turb_stator_L.stl",
                                           "turb_stator_R.stl"
                                       ],
                             "glb":  "J58.glb"
                         }
             }
}
